psutils/__init__.py
psutils/argparse.py
psutils/io.py
psutils/libpaper.py
psutils/psresources.py
psutils/readers.py
psutils/transformers.py
psutils/types.py
psutils/warnings.py
psutils/command/epsffit.py
psutils/command/extractres.py
psutils/command/includeres.py
psutils/command/psbook.py
psutils/command/psjoin.py
psutils/command/psnup.py
psutils/command/psresize.py
psutils/command/psselect.py
psutils/command/pstops.py
psutils-3.3.14.data/data/share/man/man1/epsffit.1
psutils-3.3.14.data/data/share/man/man1/extractres.1
psutils-3.3.14.data/data/share/man/man1/includeres.1
psutils-3.3.14.data/data/share/man/man1/psbook.1
psutils-3.3.14.data/data/share/man/man1/psjoin.1
psutils-3.3.14.data/data/share/man/man1/psnup.1
psutils-3.3.14.data/data/share/man/man1/psresize.1
psutils-3.3.14.data/data/share/man/man1/psselect.1
psutils-3.3.14.data/data/share/man/man1/pstops.1
psutils-3.3.14.data/data/share/man/man1/psutils.1
psutils-3.3.14.dist-info/licenses/COPYING
psutils-3.3.14.dist-info/METADATA
psutils-3.3.14.dist-info/WHEEL
psutils-3.3.14.dist-info/entry_points.txt
psutils-3.3.14.dist-info/top_level.txt
psutils-3.3.14.dist-info/RECORD
