Metadata-Version: 2.4
Name: psutils
Version: 3.3.14
Summary: Manipulate PDF and PostScript documents
Author-email: Reuben Thomas <rrt@sc3d.org>
License-Expression: GPL-3.0-or-later
Project-URL: Homepage, https://github.com/rrthomas/psutils
Classifier: Environment :: Console
Classifier: Programming Language :: Python :: 3
Requires-Python: >=3.12
License-File: COPYING
Requires-Dist: puremagic>=1.26
Requires-Dist: pypdf>=4.3.0
Provides-Extra: test
Requires-Dist: pytest-datafiles; extra == "test"
Requires-Dist: Wand; extra == "test"
Dynamic: license-file
